unsplash/__init__.py
unsplash/api.py
unsplash/auth.py
unsplash/client.py
unsplash/collection.py
unsplash/enums.py
unsplash/errors.py
unsplash/messages.py
unsplash/models.py
unsplash/photo.py
unsplash/search.py
unsplash/stat.py
unsplash/user.py
python_unsplash-1.2.5.dist-info/LICENSE
python_unsplash-1.2.5.dist-info/METADATA
python_unsplash-1.2.5.dist-info/WHEEL
python_unsplash-1.2.5.dist-info/top_level.txt
python_unsplash-1.2.5.dist-info/zip-safe
python_unsplash-1.2.5.dist-info/RECORD
