Metadata-Version: 2.1
Name: python-unsplash
Version: 1.2.5
Summary: A Python client for the Unsplash API.
Home-page: http://github.com/yakupadakli/python-unsplash.git
Author: Yakup Adaklı
Author-email: yakup.adakli@gmail.com
License: MIT
Keywords: unsplash library
Classifier: Development Status :: 5 - Production/Stable
Classifier: Topic :: Software Development :: Libraries
Classifier: License :: OSI Approved :: MIT License
Classifier: Operating System :: OS Independent
Classifier: Programming Language :: Python :: 2.7
Classifier: Programming Language :: Python :: 3.7
Classifier: Programming Language :: Python :: 3.8
Classifier: Programming Language :: Python :: 3.9
Classifier: Programming Language :: Python :: 3.11
License-File: LICENSE
